{
  "$schema": "https://schema.management.azure.com/schemas/2015-01-01/deploymentParameters.json#",
  "contentVersion": "1.0.0.0",
  "parameters": {
    "existingVNETName": {
      "value": "myVnet"
    },
    "existingSubnetName": {
      "value": "mySubnet"
    },
    "VNetResourceGroupName": {
      "value": "myVnetRGName"
    },
    "vmSize": {
      "value": "Standard_DS1_v2"
    },
    "domainJoinUserName": {
      "value": "domain\\user"
    },
    "domainJoinUserPassword": {
      "value": "password or kevault ref"
    },
    "domainFQDN": {
      "value": "domain.tld"
    },
    "vmAdminUsername": {
      "value": "vmuser"
    },
    "vmAdminPassword": {
      "value": "password or kevault ref"
    },
    "vmName": {
      "value": "myVMName"
    }
  }
}